LICENSE
MANIFEST.in
README.md
setup.py
tap_braintree/__init__.py
tap_braintree/transform.py
tap_braintree.egg-info/PKG-INFO
tap_braintree.egg-info/SOURCES.txt
tap_braintree.egg-info/dependency_links.txt
tap_braintree.egg-info/entry_points.txt
tap_braintree.egg-info/requires.txt
tap_braintree.egg-info/top_level.txt
tap_braintree/schemas/transactions.json